monju/__init__.py
monju/config.py
monju/monju.py
monju/utils.py
monju-0.3.3.dist-info/LICENSE
monju-0.3.3.dist-info/METADATA
monju-0.3.3.dist-info/WHEEL
monju-0.3.3.dist-info/top_level.txt
monju-0.3.3.dist-info/RECORD
