Metadata-Version: 2.2
Name: monju
Version: 0.3.3
Summary: A python library for brainstorming by multiple LLMs.
Home-page: https://pypi.org/project/monju/
Author: Daisuke Yamaguchi
Author-email: daicom0204@gmail.com
Project-URL: Homepage, https://habatakurikei.com/
Project-URL: GitHub, https://github.com/Habatakurikei/monju
Classifier: Development Status :: 3 - Alpha
Classifier: Intended Audience :: Developers
Classifier: License :: OSI Approved :: Apache Software License
Classifier: Operating System :: OS Independent
Classifier: Programming Language :: Python :: 3
Classifier: Programming Language :: Python :: 3.10
Classifier: Programming Language :: Python :: 3.11
Classifier: Programming Language :: Python :: 3.12
Requires-Python: >=3.10
License-File: LICENSE
Requires-Dist: llmmaster>=1.0.0
Provides-Extra: dev
Requires-Dist: pytest>=6.0; extra == "dev"
Requires-Dist: flake8>=6.0; extra == "dev"
Dynamic: author
Dynamic: author-email
Dynamic: classifier
Dynamic: description
Dynamic: description-content-type
Dynamic: home-page
Dynamic: project-url
Dynamic: provides-extra
Dynamic: requires-dist
Dynamic: requires-python
Dynamic: summary
